command_line/__init__.py
command_line/__main__.py
command_line/cli.py
command_line/config.py
command_line/extractor.py
Giturlgetter-1.0.10.dist-info/LICENSE
Giturlgetter-1.0.10.dist-info/METADATA
Giturlgetter-1.0.10.dist-info/WHEEL
Giturlgetter-1.0.10.dist-info/entry_points.txt
Giturlgetter-1.0.10.dist-info/top_level.txt
Giturlgetter-1.0.10.dist-info/RECORD
