Metadata-Version: 2.1
Name: Giturlgetter
Version: 1.0.10
Summary: Command Line to Extract the git url
Home-page: https://github.com/PrathameshDhande22/Giturlgetter
Author: Prathamesh Dhande
Author-email: prathameshdhande534@gmail.com
Keywords: git,git url,github api,url,git bash,clone url
Classifier: Development Status :: 5 - Production/Stable
Classifier: Intended Audience :: Developers
Classifier: Environment :: Console
Classifier: Operating System :: Microsoft :: Windows
Classifier: Operating System :: POSIX :: Linux
Classifier: License :: OSI Approved :: GNU General Public License v2 (GPLv2)
Classifier: Programming Language :: Python :: 3.9
Classifier: Programming Language :: Python :: 3.8
Classifier: Programming Language :: Python :: 3.10
License-File: LICENSE
Requires-Dist: PyGithub
Requires-Dist: requests
Requires-Dist: pyfiglet
Requires-Dist: python-dotenv
Requires-Dist: click
